LICENSE
MANIFEST.in
README.md
setup.py
test/__init__.py
test/test_hrp.py
torch_hrp/__init__.py
torch_hrp/hrp.py
torch_hrp.egg-info/PKG-INFO
torch_hrp.egg-info/SOURCES.txt
torch_hrp.egg-info/dependency_links.txt
torch_hrp.egg-info/requires.txt
torch_hrp.egg-info/top_level.txt
torch_hrp.egg-info/zip-safe